setup.py
tornwrap/__init__.py
tornwrap/endpoint.py
tornwrap/handler.py
tornwrap/helpers.py
tornwrap/intercom.py
tornwrap/logger.py
tornwrap/ratelimited.py
tornwrap/stripe.py
tornwrap/validated.py
tornwrap/validators.py
tornwrap.egg-info/PKG-INFO
tornwrap.egg-info/SOURCES.txt
tornwrap.egg-info/dependency_links.txt
tornwrap.egg-info/requires.txt
tornwrap.egg-info/top_level.txt
tornwrap.egg-info/zip-safe