Metadata-Version: 1.1
Name: tornwrap
Version: 0.3.5
Summary: tornado decorators and wrappers
Home-page: http://github.com/stevepeak/tornwrap
Author: @stevepeak
Author-email: steve@stevepeak.net
License: http://www.apache.org/licenses/LICENSE-2.0
Keywords: tornado tornadoweb decorators wrapper authenticated rate limited validate error handle stripe intercom
Platform: UNKNOWN
Classifier: Development Status :: 4 - Beta
Classifier: Environment :: Plugins
Classifier: Intended Audience :: Developers
Classifier: License :: OSI Approved :: Apache Software License
Classifier: Topic :: Software Development :: Testing
